math3d_bindings.cpython-38-x86_64-linux-gnu.so
wp_math3d-0.6.16.dist-info/LICENSE.txt
wp_math3d-0.6.16.dist-info/METADATA
wp_math3d-0.6.16.dist-info/RECORD
wp_math3d-0.6.16.dist-info/WHEEL
wp_math3d-0.6.16.dist-info/top_level.txt
math3d/__init__.py
