Metadata-Version: 2.1
Name: wp-math3d
Version: 0.6.16
Summary: A basic math library for spatial algebra
Home-page: https://github.com/wpumacay/loco-math
Author: Wilbert Santos Pumacay Huallpa
Author-email: wpumacay@gmail.com
License: MIT License
Keywords: math
Classifier: License :: OSI Approved :: MIT License
Classifier: Operating System :: POSIX :: Linux
Classifier: Programming Language :: Python :: 3
Classifier: Programming Language :: Python :: 3 :: Only
Classifier: Programming Language :: Python :: Implementation :: CPython
Requires-Python: >=3.7
License-File: LICENSE.txt
